maxbot/__init__.py
maxbot/bot.py
maxbot/dispatcher.py
maxbot/filters.py
maxbot/fsm.py
maxbot/router.py
maxbot/types.py
umaxbot-0.1.6.dist-info/METADATA
umaxbot-0.1.6.dist-info/WHEEL
umaxbot-0.1.6.dist-info/top_level.txt
umaxbot-0.1.6.dist-info/RECORD
