Metadata-Version: 2.4
Name: umaxbot
Version: 0.1.6
Summary: Async framework for building bots for MAX messenger (aiogram-style)
Home-page: https://github.com/werdset/maxbot
Author: werdset
Author-email: vladimirwerdset@gmail.com
Classifier: Programming Language :: Python :: 3
Classifier: Framework :: AsyncIO
Classifier: License :: OSI Approved :: MIT License
Classifier: Operating System :: OS Independent
Requires-Python: >=3.8
Requires-Dist: httpx>=0.24.0
Requires-Dist: pydantic>=1.10.0
Dynamic: author
Dynamic: author-email
Dynamic: classifier
Dynamic: description
Dynamic: description-content-type
Dynamic: home-page
Dynamic: requires-dist
Dynamic: requires-python
Dynamic: summary
